sqre_uservice_productstatus-0.0.1.dist-info/DESCRIPTION.rst
sqre_uservice_productstatus-0.0.1.dist-info/METADATA
sqre_uservice_productstatus-0.0.1.dist-info/RECORD
sqre_uservice_productstatus-0.0.1.dist-info/WHEEL
sqre_uservice_productstatus-0.0.1.dist-info/entry_points.txt
sqre_uservice_productstatus-0.0.1.dist-info/metadata.json
sqre_uservice_productstatus-0.0.1.dist-info/top_level.txt
uservice_productstatus/__init__.py
uservice_productstatus/server.py
