Metadata-Version: 2.0
Name: sqre-uservice-productstatus
Version: 0.0.1
Summary: Minimal SQuaRE API wrapper for keeper.lsst.codes product status
Home-page: https://github.com/lsst-sqre/sqre-uservice-productstatus
Author: Adam Thornton
Author-email: athornton@lsst.org
License: MIT
Keywords: lsst
Platform: UNKNOWN
Classifier: Development Status :: 4 - Beta
Classifier: Programming Language :: Python :: 2.7
Classifier: Programming Language :: Python :: 3.5
Classifier: License :: OSI Approved :: MIT License
Requires-Dist: sqre-apikit (==0.0.10)
